zibanu/django/repository/__init__.py
zibanu/django/repository/admin.py
zibanu/django/repository/apps.py
zibanu/django/repository/lib/__init__.py
zibanu/django/repository/lib/classes/__init__.py
zibanu/django/repository/lib/classes/document_generator.py
zibanu/django/repository/lib/classes/file_metadata.py
zibanu/django/repository/lib/classes/file_thumbnail.py
zibanu/django/repository/lib/controllers/__init__.py
zibanu/django/repository/lib/controllers/file_controller.py
zibanu/django/repository/lib/enums/__init__.py
zibanu/django/repository/lib/enums/access_type.py
zibanu/django/repository/lib/enums/sort_by.py
zibanu/django/repository/lib/enums/sort_type.py
zibanu/django/repository/lib/filters/__init__.py
zibanu/django/repository/lib/filters/category_list.py
zibanu/django/repository/lib/filters/parent_list.py
zibanu/django/repository/lib/managers/__init__.py
zibanu/django/repository/lib/managers/category.py
zibanu/django/repository/lib/managers/file.py
zibanu/django/repository/lib/receivers/__init__.py
zibanu/django/repository/lib/receivers/file_extended.py
zibanu/django/repository/lib/utils/__init__.py
zibanu/django/repository/lib/utils/helper.py
zibanu/django/repository/locale/es/LC_MESSAGES/django.mo
zibanu/django/repository/locale/es/LC_MESSAGES/django.po
zibanu/django/repository/migrations/0001_initial.py
zibanu/django/repository/migrations/0002_document_description.py
zibanu/django/repository/migrations/0003_category_file_fileextended_filetables_and_more.py
zibanu/django/repository/migrations/0004_remove_category_enabled.py
zibanu/django/repository/migrations/0005_alter_category_level.py
zibanu/django/repository/migrations/0006_category_uuid.py
zibanu/django/repository/migrations/0007_populate_category_uuid_values.py
zibanu/django/repository/migrations/0008_alter_category_uuid_alter_file_description.py
zibanu/django/repository/migrations/0009_file_mime_type_fileextended_ip_address_and_more.py
zibanu_django_repository-2.1.5.dist-info/licenses/LICENSE
zibanu_django_repository-2.1.5.dist-info/METADATA
zibanu_django_repository-2.1.5.dist-info/WHEEL
zibanu_django_repository-2.1.5.dist-info/top_level.txt
zibanu_django_repository-2.1.5.dist-info/RECORD
